noteyXMLParser/CreateConfig.py
noteyXMLParser/CreateDict.py
noteyXMLParser/Objects.py
noteyXMLParser/Parse.py
noteyXMLParser/__init__.py
noteyXMLParser/played_sounds.py
noteyXMLParser/test.py
noteyXMLParser/xml_parser.py
noteyXMLParser-0.2.10.dist-info/LICENSE
noteyXMLParser-0.2.10.dist-info/METADATA
noteyXMLParser-0.2.10.dist-info/WHEEL
noteyXMLParser-0.2.10.dist-info/top_level.txt
noteyXMLParser-0.2.10.dist-info/RECORD
