Metadata-Version: 2.1
Name: noteyXMLParser
Version: 0.2.10
Summary: Music XML Parser
Home-page: https://github.com/mmahjoub5/NoteyXMLParser
Author: Amin Mahjoub
Author-email: mahjoub@usc.edu
License: UNKNOWN
Platform: UNKNOWN
Classifier: Programming Language :: Python :: 3
Classifier: License :: OSI Approved :: MIT License
Classifier: Operating System :: OS Independent
